LICENSE
MANIFEST.in
README.rst
find_similar_images.py
setup.py
ImageHashCache.egg-info/PKG-INFO
ImageHashCache.egg-info/SOURCES.txt
ImageHashCache.egg-info/dependency_links.txt
ImageHashCache.egg-info/requires.txt
ImageHashCache.egg-info/top_level.txt
imagehashcache/__init__.py
imagehashcache/util.py