Metadata-Version: 1.0
Name: ImageHashCache
Version: 0.1.0
Summary: Image Hashing Library with Cache
Home-page: https://github.com/jzbjyb/imagehash
Author: Zhengbao Jiang
Author-email: rucjzb@163.com
License: LICENSE
Platform: UNKNOWN
